bruttle/__init__.py
bruttle/bruttle.py
bruttle-1.0.0.dist-info/LICENSE
bruttle-1.0.0.dist-info/METADATA
bruttle-1.0.0.dist-info/WHEEL
bruttle-1.0.0.dist-info/entry_points.txt
bruttle-1.0.0.dist-info/RECORD
