Metadata-Version: 2.1
Name: bruttle
Version: 1.0.0
Summary: A cli app to bruteforce pdf, zip, and some common hashes
Home-page: https://github.com/tamton-aquib/bruttle
License: MIT
Keywords: pdf,zip,hash,crack,bruteeforce,brute force
Author: Aquib
Author-email: aquibjavedt007@gmail.com
Requires-Python: >=3.11
Classifier: License :: OSI Approved :: MIT License
Classifier: Programming Language :: Python :: 3
Classifier: Programming Language :: Python :: 3.11
Classifier: Programming Language :: Python :: 3.12
Requires-Dist: pikepdf (==8.13.0)
Requires-Dist: tqdm (==4.66.2)
Project-URL: Documentation, https://github.com/tamton-aquib/bruttle
